chik_clvm_tools/NodePath.py
chik_clvm_tools/__init__.py
chik_clvm_tools/binutils.py
chik_clvm_tools/clvmc.py
chik_clvm_tools/cmds.py
chik_clvm_tools/curry.py
chik_clvm_tools/debug.py
chik_clvm_tools/operator_dict.py
chik_clvm_tools/pattern_match.py
chik_clvm_tools/py.typed
chik_clvm_tools/sha256tree.py
chik_clvm_tools/setuptools/__init__.py
chik_clvm_tools/setuptools/build_clvm.py
chik_clvm_tools/setuptools/patch_build_ext.py
chik_clvm_tools/setuptools/patched_build_ext.py
ir/Type.py
ir/__init__.py
ir/py.typed
ir/reader.py
ir/utils.py
ir/writer.py
stages/__init__.py
stages/py.typed
stages/stage_0.py
stages/stage_2/__init__.py
stages/stage_2/bindings.py
stages/stage_2/compile.py
stages/stage_2/defaults.py
stages/stage_2/helpers.py
stages/stage_2/mod.py
stages/stage_2/operators.py
stages/stage_2/optimize.py
chik_clvm_tools-0.4.6.dist-info/LICENSE
chik_clvm_tools-0.4.6.dist-info/METADATA
chik_clvm_tools-0.4.6.dist-info/WHEEL
chik_clvm_tools-0.4.6.dist-info/entry_points.txt
chik_clvm_tools-0.4.6.dist-info/top_level.txt
chik_clvm_tools-0.4.6.dist-info/RECORD
