Metadata-Version: 2.1
Name: chik-clvm-tools
Version: 0.4.6
Summary: CLVM compiler.
Home-page: https://github.com/Chik-Network
Author: Chik Network, Inc.
Author-email: kiss@chiknetwork.com
License: https://opensource.org/licenses/Apache-2.0
Project-URL: Bug Reports, https://github.com/Chik-Network/chik_clvm_tools
Project-URL: Source, https://github.com/Chik-Network/chik_clvm_tools
Classifier: Development Status :: 3 - Alpha
Classifier: Programming Language :: Python :: 3
Classifier: Programming Language :: Python :: 3.6
Classifier: Programming Language :: Python :: 3.7
Classifier: License :: OSI Approved :: Apache Software License
Classifier: Topic :: Security :: Cryptography
License-File: LICENSE
Requires-Dist: clvm (>=0.9.2)
Requires-Dist: chik-clvm-tools-rs (>=0.1.25)
Provides-Extra: dev
Requires-Dist: pytest ; extra == 'dev'
